googleanswer/__init__.py
googleanswer-1.5.dist-info/LICENSE.txt
googleanswer-1.5.dist-info/METADATA
googleanswer-1.5.dist-info/WHEEL
googleanswer-1.5.dist-info/top_level.txt
googleanswer-1.5.dist-info/RECORD
