Metadata-Version: 2.1
Name: googleanswer
Version: 1.5
Summary: The supreme Google Search API
Home-page: https://github.com/sanat-garg/google_search
Author: Sanat Garg
Author-email: sanatgarg11@gmail.com
License: UNKNOWN
Project-URL: Google Search, https://github.com/sanat-garg/google_search
Platform: UNKNOWN
Classifier: Programming Language :: Python :: 3
Classifier: License :: OSI Approved :: MIT License
Classifier: Operating System :: OS Independent
Requires-Python: >=3.0
Requires-Dist: requests
